spl/__init__.py
spl/postegres/__init__.py
spl/postegres/adpter.py
shared_python_library-1.0.1.dist-info/METADATA
shared_python_library-1.0.1.dist-info/WHEEL
shared_python_library-1.0.1.dist-info/top_level.txt
shared_python_library-1.0.1.dist-info/RECORD
