Metadata-Version: 2.1
Name: shared-python-library
Version: 1.0.1
Summary: # airtech-shared-python-library
Author: airtech
Keywords: shared,library,postgres
Classifier: Development Status :: 3 - Alpha
Classifier: Intended Audience :: Developers
Classifier: Programming Language :: Python :: 3
Classifier: Programming Language :: Python :: 3.7
Classifier: Programming Language :: Python :: 3.8
Classifier: Programming Language :: Python :: 3.9
Classifier: Programming Language :: Python :: 3.10
Classifier: Programming Language :: Python :: 3 :: Only
Requires-Python: >=3.7, <4
Requires-Dist: psycop2 ==2.9.9
